{
  "emailErrorLimit": 6,
  "devices": [
    {
      "name": "L3L4",
      "ip": "10.139.208.69",
      "output": "   10.139.208.69 : Connected - Ping: 1ms",
      "consecErrors": 0
    },
    {
      "name": "Core2",
      "ip": "10.139.208.64",
      "output": "   10.139.208.64 : Connected - Ping: 1ms",
      "consecErrors": 0
    },
    {
      "name": "VCAL",
      "ip": "10.139.208.72",
      "output": "   10.139.208.72 : Connected - Ping: 176ms",
      "consecErrors": 0
    },
    {
      "name": "Workshop",
      "ip": "10.139.208.85",
      "output": "   10.139.208.85 : Connected - Ping: 10ms",
      "consecErrors": 0
    }
  ],
  "emailFrom": "device.monitor.mail@gmail.com",
  "emailPassword": "Dev!ceM0nitor",
  "emailTo": [
    "lee.ben.b@edumail.vic.gov.au"
  ],
  "host": "smtp.gmail.com",
  "port": 587
}
